Workbook
Name SegmentaçãodeDados_Age_Group: #N/A
Name SegmentaçãodeDados_JobLevel: #N/A

Sheet Assets
C2: Panel Background | F2: Cards and Menus | I2: Alerts / Turnover
B3: #f2f2f2 | E3: #305496 | H3: #ff9900
B5: Age Group | E5: What is the monthly income amount by age group? | T5: =Assets!H36 -> 9559309
B6: Minimum Age | C6: Category | H6: Age Range | I6: Sum of Monthly Income
B7: 18 | C7: 18 to 25 years old | H7: 18 to 25 years old | I7: 365665
B8: 26 | C8: 26 to 35 years old | H8: 26 to 35 years old | I8: 2966754
B9: 36 | C9: 36 to 45 years old | H9: 36 to 45 years old | I9: 3324880
B10: 46 | C10: 46 to 55 years old | H10: 46 to 55 years old | I10: 2469719
B11: 56 | C11: 56 years or older | H11: 56 years or older | I11: 432291
H12: Grand total | I12: 9559309
B21: Salary Range | E21: What is the number of people per salary range?
B22: Minimum Limit | C22: Salary Range | H22: Job Level | I22: Sum od Monthly Income
B23: 0 | C23: Up to $3.000 | H23: 1 | I23: 1513295
B24: 3001 | C24: $3.001 to $7.000 | H24: 2 | I24: 2938216
B25: 7001 | C25: $7.001 to $12.000 | H25: 3 | I25: 2140161
B26: 12001 | C26: Over $12.000 | H26: 4 | I26: 1643401
H27: 5 | I27: 1324236
H28: Grand Total | I28: 9559309
B29: What is the total monthly income?
C32: Job Level
C33: 1 | D33: 2 | E33: 3 | F33: 4 | G33: 5 | H33: Grand Total
B34: Sum of Monthly Income | C34: 1513295 | D34: 2938216 | E34: 2140161 | F34: 1643401 | G34: 1324236 | H34: 9559309
H36: =GETPIVOTDATA("MonthlyIncome",$B$32) -> 9559309
C38: Age Range
C39: 18 to 25 years old | D39: 26 to 35 years old | E39: 36 to 45 years old | F39: 46 to 55 years old | G39: 56 years or older | H39: Grand Total
B40: Sum of Monthly Income | C40: 365665 | D40: 2966754 | E40: 3324880 | F40: 2469719 | G40: 432291 | H40: 9559309
H42: =GETPIVOTDATA("MonthlyIncome",$B$38) -> 9559309

Sheet Base
A1: Age | B1: Attrition | C1: BusinessTravel | D1: DailyRate | E1: Department | F1: DistanceFromHome | G1: Education | H1: EducationField | I1: EmployeeCount | J1: EmployeeNumber | K1: EnvironmentSatisfaction | L1: Gender | M1: HourlyRate | N1: JobInvolvement | O1: JobLevel | P1: JobRole | Q1: JobSatisfaction | R1: MaritalStatus | S1: MonthlyIncome | T1: MonthlyRate | U1: NumCompaniesWorked | V1: Over18 | W1: OverTime | X1: PercentSalaryHike | Y1: PerformanceRating | Z1: RelationshipSatisfaction | AA1: StandardHours | AB1: StockOptionLevel | AC1: TotalWorkingYears | AD1: TrainingTimesLastYear | AE1: WorkLifeBalance | AF1: YearsAtCompany | AG1: YearsInCurrentRole | AH1: YearsSinceLastPromotion | AI1: YearsWithCurrManager | AJ1: Age Group | AK1: Salary Group
A2: 41 | B2: Yes | C2: Travel_Rarely | D2: 1102 | E2: Sales | F2: 1 | G2: 2 | H2: Life Sciences | I2: 1 | J2: 1 | K2: 2 | L2: Female | M2: 94 | N2: 3 | O2: 2 | P2: Sales Executive | Q2: 4 | R2: Single | S2: 5993 | T2: 19479 | U2: 8 | V2: Y | W2: Yes | X2: 11 | Y2: 3 | Z2: 1 | AA2: 80 | AB2: 0 | AC2: 8 | AD2: 0 | AE2: 1 | AF2: 6 | AG2: 4 | AH2: 0 | AI2: 5 | AJ2: =VLOOKUP(A2,Assets!$B$7:$C$11,2,TRUE) -> 36 to 45 years old | AK2: =VLOOKUP(S2,Assets!$B$11:$C$26,2,TRUE) -> $3.001 to $7.000
A3: 49 | B3: No | C3: Travel_Frequently | D3: 279 | E3: Research & Development | F3: 8 | G3: 1 | H3: Life Sciences | I3: 1 | J3: 2 | K3: 3 | L3: Male | M3: 61 | N3: 2 | O3: 2 | P3: Research Scientist | Q3: 2 | R3: Married | S3: 5130 | T3: 24907 | U3: 1 | V3: Y | W3: No | X3: 23 | Y3: 4 | Z3: 4 | AA3: 80 | AB3: 1 | AC3: 10 | AD3: 3 | AE3: 3 | AF3: 10 | AG3: 7 | AH3: 1 | AI3: 7 | AJ3: =VLOOKUP(A3,Assets!$B$7:$C$11,2,TRUE) -> 46 to 55 years old | AK3: =VLOOKUP(S3,Assets!$B$11:$C$26,2,TRUE) -> $3.001 to $7.000
A4: 37 | B4: Yes | C4: Travel_Rarely | D4: 1373 | E4: Research & Development | F4: 2 | G4: 2 | H4: Other | I4: 1 | J4: 4 | K4: 4 | L4: Male | M4: 92 | N4: 2 | O4: 1 | P4: Laboratory Technician | Q4: 3 | R4: Single | S4: 2090 | T4: 2396 | U4: 6 | V4: Y | W4: Yes | X4: 15 | Y4: 3 | Z4: 2 | AA4: 80 | AB4: 0 | AC4: 7 | AD4: 3 | AE4: 3 | AF4: 0 | AG4: 0 | AH4: 0 | AI4: 0 | AJ4: =VLOOKUP(A4,Assets!$B$7:$C$11,2,TRUE) -> 36 to 45 years old | AK4: =VLOOKUP(S4,Assets!$B$11:$C$26,2,TRUE) -> Up to $3.000
A5: 33 | B5: No | C5: Travel_Frequently | D5: 1392 | E5: Research & Development | F5: 3 | G5: 4 | H5: Life Sciences | I5: 1 | J5: 5 | K5: 4 | L5: Female | M5: 56 | N5: 3 | O5: 1 | P5: Research Scientist | Q5: 3 | R5: Married | S5: 2909 | T5: 23159 | U5: 1 | V5: Y | W5: Yes | X5: 11 | Y5: 3 | Z5: 3 | AA5: 80 | AB5: 0 | AC5: 8 | AD5: 3 | AE5: 3 | AF5: 8 | AG5: 7 | AH5: 3 | AI5: 0 | AJ5: =VLOOKUP(A5,Assets!$B$7:$C$11,2,TRUE) -> 26 to 35 years old | AK5: =VLOOKUP(S5,Assets!$B$11:$C$26,2,TRUE) -> Up to $3.000
A6: 27 | B6: No | C6: Travel_Rarely | D6: 591 | E6: Research & Development | F6: 2 | G6: 1 | H6: Medical | I6: 1 | J6: 7 | K6: 1 | L6: Male | M6: 40 | N6: 3 | O6: 1 | P6: Laboratory Technician | Q6: 2 | R6: Married | S6: 3468 | T6: 16632 | U6: 9 | V6: Y | W6: No | X6: 12 | Y6: 3 | Z6: 4 | AA6: 80 | AB6: 1 | AC6: 6 | AD6: 3 | AE6: 3 | AF6: 2 | AG6: 2 | AH6: 2 | AI6: 2 | AJ6: =VLOOKUP(A6,Assets!$B$7:$C$11,2,TRUE) -> 26 to 35 years old | AK6: =VLOOKUP(S6,Assets!$B$11:$C$26,2,TRUE) -> $3.001 to $7.000
A7: 32 | B7: No | C7: Travel_Frequently | D7: 1005 | E7: Research & Development | F7: 2 | G7: 2 | H7: Life Sciences | I7: 1 | J7: 8 | K7: 4 | L7: Male | M7: 79 | N7: 3 | O7: 1 | P7: Laboratory Technician | Q7: 4 | R7: Single | S7: 3068 | T7: 11864 | U7: 0 | V7: Y | W7: No | X7: 13 | Y7: 3 | Z7: 3 | AA7: 80 | AB7: 0 | AC7: 8 | AD7: 2 | AE7: 2 | AF7: 7 | AG7: 7 | AH7: 3 | AI7: 6 | AJ7: =VLOOKUP(A7,Assets!$B$7:$C$11,2,TRUE) -> 26 to 35 years old | AK7: =VLOOKUP(S7,Assets!$B$11:$C$26,2,TRUE) -> $3.001 to $7.000
A8: 59 | B8: No | C8: Travel_Rarely | D8: 1324 | E8: Research & Development | F8: 3 | G8: 3 | H8: Medical | I8: 1 | J8: 10 | K8: 3 | L8: Female | M8: 81 | N8: 4 | O8: 1 | P8: Laboratory Technician | Q8: 1 | R8: Married | S8: 2670 | T8: 9964 | U8: 4 | V8: Y | W8: Yes | X8: 20 | Y8: 4 | Z8: 1 | AA8: 80 | AB8: 3 | AC8: 12 | AD8: 3 | AE8: 2 | AF8: 1 | AG8: 0 | AH8: 0 | AI8: 0 | AJ8: =VLOOKUP(A8,Assets!$B$7:$C$11,2,TRUE) -> 56 years or older | AK8: =VLOOKUP(S8,Assets!$B$11:$C$26,2,TRUE) -> Up to $3.000
A9: 30 | B9: No | C9: Travel_Rarely | D9: 1358 | E9: Research & Development | F9: 24 | G9: 1 | H9: Life Sciences | I9: 1 | J9: 11 | K9: 4 | L9: Male | M9: 67 | N9: 3 | O9: 1 | P9: Laboratory Technician | Q9: 3 | R9: Divorced | S9: 2693 | T9: 13335 | U9: 1 | V9: Y | W9: No | X9: 22 | Y9: 4 | Z9: 2 | AA9: 80 | AB9: 1 | AC9: 1 | AD9: 2 | AE9: 3 | AF9: 1 | AG9: 0 | AH9: 0 | AI9: 0 | AJ9: =VLOOKUP(A9,Assets!$B$7:$C$11,2,TRUE) -> 26 to 35 years old | AK9: =VLOOKUP(S9,Assets!$B$11:$C$26,2,TRUE) -> Up to $3.000
A10: 38 | B10: No | C10: Travel_Frequently | D10: 216 | E10: Research & Development | F10: 23 | G10: 3 | H10: Life Sciences | I10: 1 | J10: 12 | K10: 4 | L10: Male | M10: 44 | N10: 2 | O10: 3 | P10: Manufacturing Director | Q10: 3 | R10: Single | S10: 9526 | T10: 8787 | U10: 0 | V10: Y | W10: No | X10: 21 | Y10: 4 | Z10: 2 | AA10: 80 | AB10: 0 | AC10: 10 | AD10: 2 | AE10: 3 | AF10: 9 | AG10: 7 | AH10: 1 | AI10: 8 | AJ10: =VLOOKUP(A10,Assets!$B$7:$C$11,2,TRUE) -> 36 to 45 years old | AK10: =VLOOKUP(S10,Assets!$B$11:$C$26,2,TRUE) -> $7.001 to $12.000
A11: 36 | B11: No | C11: Travel_Rarely | D11: 1299 | E11: Research & Development | F11: 27 | G11: 3 | H11: Medical | I11: 1 | J11: 13 | K11: 3 | L11: Male | M11: 94 | N11: 3 | O11: 2 | P11: Healthcare Representative | Q11: 3 | R11: Married | S11: 5237 | T11: 16577 | U11: 6 | V11: Y | W11: No | X11: 13 | Y11: 3 | Z11: 2 | AA11: 80 | AB11: 2 | AC11: 17 | AD11: 3 | AE11: 2 | AF11: 7 | AG11: 7 | AH11: 7 | AI11: 7 | AJ11: =VLOOKUP(A11,Assets!$B$7:$C$11,2,TRUE) -> 36 to 45 years old | AK11: =VLOOKUP(S11,Assets!$B$11:$C$26,2,TRUE) -> $3.001 to $7.000
A12: 35 | B12: No | C12: Travel_Rarely | D12: 809 | E12: Research & Development | F12: 16 | G12: 3 | H12: Medical | I12: 1 | J12: 14 | K12: 1 | L12: Male | M12: 84 | N12: 4 | O12: 1 | P12: Laboratory Technician | Q12: 2 | R12: Married | S12: 2426 | T12: 16479 | U12: 0 | V12: Y | W12: No | X12: 13 | Y12: 3 | Z12: 3 | AA12: 80 | AB12: 1 | AC12: 6 | AD12: 5 | AE12: 3 | AF12: 5 | AG12: 4 | AH12: 0 | AI12: 3 | AJ12: =VLOOKUP(A12,Assets!$B$7:$C$11,2,TRUE) -> 26 to 35 years old | AK12: =VLOOKUP(S12,Assets!$B$11:$C$26,2,TRUE) -> Up to $3.000
A13: 29 | B13: No | C13: Travel_Rarely | D13: 153 | E13: Research & Development | F13: 15 | G13: 2 | H13: Life Sciences | I13: 1 | J13: 15 | K13: 4 | L13: Female | M13: 49 | N13: 2 | O13: 2 | P13: Laboratory Technician | Q13: 3 | R13: Single | S13: 4193 | T13: 12682 | U13: 0 | V13: Y | W13: Yes | X13: 12 | Y13: 3 | Z13: 4 | AA13: 80 | AB13: 0 | AC13: 10 | AD13: 3 | AE13: 3 | AF13: 9 | AG13: 5 | AH13: 0 | AI13: 8 | AJ13: =VLOOKUP(A13,Assets!$B$7:$C$11,2,TRUE) -> 26 to 35 years old | AK13: =VLOOKUP(S13,Assets!$B$11:$C$26,2,TRUE) -> $3.001 to $7.000
... A1471: 34 | B1471: No | C1471: Travel_Rarely | D1471: 628 | E1471: Research & Development | F1471: 8 | G1471: 3 | H1471: Medical | I1471: 1 | J1471: 2068 | K1471: 2 | L1471: Male | M1471: 82 | N1471: 4 | O1471: 2 | P1471: Laboratory Technician | Q1471: 3 | R1471: Married | S1471: 4404 | T1471: 10228 | U1471: 2 | V1471: Y | W1471: No | X1471: 12 | Y1471: 3 | Z1471: 1 | AA1471: 80 | AB1471: 0 | AC1471: 6 | AD1471: 3 | AE1471: 4 | AF1471: 4 | AG1471: 3 | AH1471: 1 | AI1471: 2 | AJ1471: =VLOOKUP(A1471,Assets!$B$7:$C$11,2,TRUE) -> 26 to 35 years old | AK1471: =VLOOKUP(S1471,Assets!$B$11:$C$26,2,TRUE) -> $3.001 to $7.000

Sheet Dashboard
C2: PEOPLE ANALYTICS
